sigma/__init__.py
sigma/sigma_a.py
sigma/sigma_b.py
sigma_test-0.0.1.dist-info/METADATA
sigma_test-0.0.1.dist-info/WHEEL
sigma_test-0.0.1.dist-info/top_level.txt
sigma_test-0.0.1.dist-info/RECORD
