Metadata-Version: 2.1
Name: sigma-test
Version: 0.0.1
Summary: This is an Sigma Package
Home-page: UNKNOWN
Author: AlanRick
Author-email: zs13128488417@gmail.com
License: UNKNOWN
Platform: UNKNOWN
Requires-Dist: requests
